poslog/AbstractPosTagger.py
poslog/PosLogCRF.py
poslog/PosLogTokenizer.py
poslog/__init__.py
poslog/__main__.py
poslog/models/pos_log_upos_crf_10k_model.pkl
poslog/words/KnownWordsDetector.py
poslog/words/RegexTokenClassMatcher.py
poslog/words/__init__.py
poslog/words/known_domain_words.txt
poslog-0.7.dist-info/licenses/LICENSE
poslog-0.7.dist-info/METADATA
poslog-0.7.dist-info/WHEEL
poslog-0.7.dist-info/top_level.txt
poslog-0.7.dist-info/RECORD
