Metadata-Version: 2.4
Name: poslog
Version: 0.7
Summary: PosLog: A CRF-based Part-of-Speech Tagger for Log Messages
Author: Kilian Dangendorf
Project-URL: GitHub, https://github.com/kiliandangendorf/poslog
Requires-Python: >=3.11
License-File: LICENSE
Requires-Dist: nltk
Requires-Dist: sklearn-crfsuite
Dynamic: author
Dynamic: description
Dynamic: description-content-type
Dynamic: license-file
Dynamic: project-url
Dynamic: requires-dist
Dynamic: requires-python
Dynamic: summary
